AgeraWikiZhongwenbanV10/README.md
AgeraWikiZhongwenbanV10/__init__.py
AgeraWikiZhongwenbanV10/__main__.py
AgeraWikiZhongwenbanV10/file.epub
AgeraWikiZhongwenbanV10/index.html
AgeraWikiZhongwenbanV10/css/__init__.py
AgeraWikiZhongwenbanV10/css/annotations.css
AgeraWikiZhongwenbanV10/css/main.css
AgeraWikiZhongwenbanV10/css/normalize.css
AgeraWikiZhongwenbanV10/css/popup.css
AgeraWikiZhongwenbanV10/font/__init__.py
AgeraWikiZhongwenbanV10/font/fontello.eot
AgeraWikiZhongwenbanV10/font/fontello.svg
AgeraWikiZhongwenbanV10/font/fontello.ttf
AgeraWikiZhongwenbanV10/font/fontello.woff
AgeraWikiZhongwenbanV10/img/__init__.py
AgeraWikiZhongwenbanV10/img/annotator-glyph-sprite.png
AgeraWikiZhongwenbanV10/img/annotator-icon-sprite.png
AgeraWikiZhongwenbanV10/img/apple-touch-icon.png
AgeraWikiZhongwenbanV10/img/cancelfullscreen.png
AgeraWikiZhongwenbanV10/img/close.png
AgeraWikiZhongwenbanV10/img/fullscreen.png
AgeraWikiZhongwenbanV10/img/loader.gif
AgeraWikiZhongwenbanV10/img/menu-icon.png
AgeraWikiZhongwenbanV10/img/save.png
AgeraWikiZhongwenbanV10/img/saved.png
AgeraWikiZhongwenbanV10/img/settings-s.png
AgeraWikiZhongwenbanV10/img/settings.png
AgeraWikiZhongwenbanV10/img/star.png
AgeraWikiZhongwenbanV10/js/__init__.py
AgeraWikiZhongwenbanV10/js/epub.js
AgeraWikiZhongwenbanV10/js/epub.min.js
AgeraWikiZhongwenbanV10/js/epub.min.map
AgeraWikiZhongwenbanV10/js/hooks.min.js
AgeraWikiZhongwenbanV10/js/hooks.min.map
AgeraWikiZhongwenbanV10/js/reader.js
AgeraWikiZhongwenbanV10/js/reader.js.map
AgeraWikiZhongwenbanV10/js/reader.min.js
AgeraWikiZhongwenbanV10/js/reader.min.map
AgeraWikiZhongwenbanV10/js/hooks/__init__.py
AgeraWikiZhongwenbanV10/js/hooks/extensions/__init__.py
AgeraWikiZhongwenbanV10/js/hooks/extensions/highlight.js
AgeraWikiZhongwenbanV10/js/libs/__init__.py
AgeraWikiZhongwenbanV10/js/libs/jquery.min.js
AgeraWikiZhongwenbanV10/js/libs/localforage.min.js
AgeraWikiZhongwenbanV10/js/libs/screenfull.js
AgeraWikiZhongwenbanV10/js/libs/screenfull.min.js
agera_wiki_zhongwenban_v1_0-2024.2.29.0.dist-info/METADATA
agera_wiki_zhongwenban_v1_0-2024.2.29.0.dist-info/WHEEL
agera_wiki_zhongwenban_v1_0-2024.2.29.0.dist-info/entry_points.txt
agera_wiki_zhongwenban_v1_0-2024.2.29.0.dist-info/top_level.txt
agera_wiki_zhongwenban_v1_0-2024.2.29.0.dist-info/RECORD
